multirate_throttling/__init__.py
multirate_throttling/throttles.py
multirate_throttling-0.1.3.dist-info/METADATA
multirate_throttling-0.1.3.dist-info/WHEEL
multirate_throttling-0.1.3.dist-info/top_level.txt
multirate_throttling-0.1.3.dist-info/RECORD
