Metadata-Version: 2.1
Name: multirate-throttling
Version: 0.1.3
Summary: Multi-rate throttle for Django Rest Framework
Author-email: UNICC <cps@unicc.org>
Classifier: Development Status :: 4 - Beta
Classifier: Intended Audience :: Developers
Classifier: Natural Language :: English
Classifier: Programming Language :: Python :: 3
Classifier: Programming Language :: Python :: 3.8
Classifier: Programming Language :: Python :: 3.9
Classifier: Programming Language :: Python :: 3.10
Classifier: Programming Language :: Python :: 3.11
Requires-Python: >=3.8
Requires-Dist: Django >=3.2
Requires-Dist: djangorestframework >=3.10
Provides-Extra: dev
Requires-Dist: isort >=5.12.0 ; extra == 'dev'
Requires-Dist: black >=23.7.0 ; extra == 'dev'
Requires-Dist: flake8-pyproject >=1.2.3 ; extra == 'dev'
Provides-Extra: test
Requires-Dist: pytest >=7.4.0 ; extra == 'test'
Requires-Dist: pytest-mock >=3.11.1 ; extra == 'test'
Requires-Dist: pytest-cov >=4.1.0 ; extra == 'test'
